LICENSE
pyproject.toml
readme.md
src/prometheus_exporter/__init__.py
src/prometheus_exporter/cached_exporter.py
src/prometheus_exporter/exporter.py
src/prometheus_exporter/labels.py
src/prometheus_exporter/main.py
src/prometheus_exporter/metric.py
src/prometheus_exporter.egg-info/PKG-INFO
src/prometheus_exporter.egg-info/SOURCES.txt
src/prometheus_exporter.egg-info/dependency_links.txt
src/prometheus_exporter.egg-info/entry_points.txt
src/prometheus_exporter.egg-info/requires.txt
src/prometheus_exporter.egg-info/top_level.txt