Metadata-Version: 2.1
Name: prometheus_exporter
Version: 0.13.0
Summary: A Python library for exporting data as metrics for Prometheus
Author-email: Desultory <dev@pyl.onl>
Classifier: Programming Language :: Python :: 3
Classifier: License :: OSI Approved :: GNU General Public License v2 (GPLv2)
Classifier: Operating System :: OS Independent
Requires-Python: >=3.11
License-File: LICENSE
Requires-Dist: zenlib>=1.6.5
Requires-Dist: aiohttp>=3.9.1
